astrometapy/__init__.py
astrometapy/cli.py
astrometapy/cleaners/__init__.py
astrometapy/cleaners/schema_unifier.py
astrometapy/cleaners/validator.py
astrometapy/exporters/__init__.py
astrometapy/exporters/to_csv.py
astrometapy/exporters/to_json.py
astrometapy/exporters/to_votable.py
astrometapy/readers/__init__.py
astrometapy/readers/catalog_reader.py
astrometapy/readers/fits_reader.py
astrometapy/readers/votable_reader.py
astrometapy/utils/__init__.py
astrometapy/utils/logger.py
astrometapy-0.1.0.dist-info/licenses/LICENSE
tests/__init__.py
tests/test_fits_reader.py
astrometapy-0.1.0.dist-info/METADATA
astrometapy-0.1.0.dist-info/WHEEL
astrometapy-0.1.0.dist-info/top_level.txt
astrometapy-0.1.0.dist-info/RECORD
