Metadata-Version: 2.4
Name: astrometapy
Version: 0.1.0
Summary: A Python package for reading, cleaning, and exporting astronomical metadata.
Home-page: https://github.com/whiteflakes/astrometapy
Author: Whiteflakes
Author-email: Whiteflakes <whiteflakesdev@gmail.com>
License: MIT
Classifier: Programming Language :: Python :: 3
Classifier: License :: OSI Approved :: MIT License
Classifier: Operating System :: OS Independent
Requires-Python: >=3.7
License-File: LICENSE
Requires-Dist: astropy
Requires-Dist: pandas
Requires-Dist: jsonschema
Requires-Dist: typer
Dynamic: author
Dynamic: home-page
Dynamic: license-file
Dynamic: requires-python
